easypymongodb/__init__.py
easypymongodb/setup.py
easypymongodb-0.1.6.dist-info/METADATA
easypymongodb-0.1.6.dist-info/WHEEL
easypymongodb-0.1.6.dist-info/top_level.txt
easypymongodb-0.1.6.dist-info/RECORD
