Metadata-Version: 2.1
Name: easypymongodb
Version: 0.1.6
Summary: A package that simplifies the use of the pymongo library.
Home-page: https://github.com/Zeliktric/easypymongodb
Author: Zeliktric
Author-email: zeliktric@gmail.com
License: UNKNOWN
Keywords: DB,database,mongo,pymongo,easypymongodb,python,db
Platform: UNKNOWN
Classifier: Programming Language :: Python :: 3
Classifier: License :: OSI Approved :: MIT License
Classifier: Operating System :: OS Independent
Requires-Python: >=3.6
Requires-Dist: pymongo
Requires-Dist: dnspython
